common_agent_code/__init__.py
common_agent_code/backend/__init__.py
common_agent_code/backend/app.py
common_agent_code/backend/config.py
common_agent_code/backend/models.py
common_agent_code/backend/database/__init__.py
common_agent_code/backend/database/init_db.py
common_agent_code/backend/routes/__init__.py
common_agent_code/backend/routes/create_agent_definitions.py
common_agent_code/backend/routes/create_conversation.py
common_agent_code/backend/routes/delete_agent_definition.py
common_agent_code/backend/routes/delete_conversation.py
common_agent_code/backend/routes/get_agent_conversations.py
common_agent_code/backend/routes/get_agent_definitions.py
common_agent_code/backend/routes/get_available_agents.py
common_agent_code/backend/routes/get_conversation.py
common_agent_code/backend/routes/get_conversation_history.py
common_agent_code/backend/routes/get_conversation_messages.py
common_agent_code/backend/routes/get_conversations.py
common_agent_code/backend/routes/get_message_objects.py
common_agent_code/backend/routes/home.py
common_agent_code/backend/routes/new_conversation.py
common_agent_code/backend/routes/restore_state_from_message.py
common_agent_code/backend/routes/send_message.py
common_agent_code/backend/routes/start_conversation.py
common_agent_code/backend/routes/update_agent_definitions.py
common_agent_code/backend/routes/upload_file.py
common_agent_code/backend/services/__init__.py
common_agent_code/backend/services/faiss_service.py
common_agent_code/backend/services/graph_service.py
common_agent_code/backend/services/llm_service.py
common_agent_code/backend/services/nlp_service.py
common_agent_code/backend/services/openai_client.py
common_agent_code/backend/services/pdf_service.py
common_agent_code/backend/services/visualization_service.py
common_agent_code/backend/services/web_service.py
common_agent_code/backend/utils/AgentState.py
common_agent_code/backend/utils/CustomJSONEncoder.py
common_agent_code/backend/utils/ExecutionResult.py
common_agent_code-0.1.17.dist-info/METADATA
common_agent_code-0.1.17.dist-info/WHEEL
common_agent_code-0.1.17.dist-info/top_level.txt
common_agent_code-0.1.17.dist-info/RECORD
