Metadata-Version: 2.4
Name: common-agent-code
Version: 0.1.17
Summary: Modular backend agent framework for LLM-driven chat systems
Author-email: Tejas Krishnamoorthy <tejaskrishnamoorthy@gmail.com>
Requires-Python: >=3.8
Requires-Dist: flask
Requires-Dist: flask-sqlalchemy
Requires-Dist: flask-cors
Requires-Dist: python-dotenv
Requires-Dist: nltk
Requires-Dist: faiss-cpu
Requires-Dist: sentence-transformers
Requires-Dist: matplotlib
Requires-Dist: pdfminer.six
Requires-Dist: pandas
Requires-Dist: numpy
Requires-Dist: scikit-learn
Requires-Dist: plotly
Requires-Dist: PyYAML
Requires-Dist: requests
Requires-Dist: openai
Requires-Dist: PyPDF2
Requires-Dist: joblib
Requires-Dist: networkx
Requires-Dist: beautifulsoup4
Requires-Dist: regex
Requires-Dist: tqdm
Provides-Extra: dev
Requires-Dist: pytest; extra == "dev"
Requires-Dist: build; extra == "dev"
Requires-Dist: twine; extra == "dev"
Requires-Dist: wheel; extra == "dev"
